spb/__init__.py
spb/check_params_spb.py
spb/spb.py
spb-0.1.1.dist-info/AUTHORS
spb-0.1.1.dist-info/LICENSE
spb-0.1.1.dist-info/METADATA
spb-0.1.1.dist-info/WHEEL
spb-0.1.1.dist-info/top_level.txt
spb-0.1.1.dist-info/RECORD
