Metadata-Version: 2.1
Name: spb
Version: 0.1.1
Summary: Simple Progress Bar
Home-page: https://github.com/patsuckow/spb
Author: Alexey Patsukov 🇷🇺
Author-email: patsuckow@yandex.ru
License: GNU General Public License v3 (GPLv3)
Download-URL: https://github.com/patsuckow/spb/arhive/0.1.1.tar.gz
Keywords: progress,progress bar,progressbar,progress indicator,percent indicator,progressmeter,timer indicator,eta,data rate indicator,transmitted data indicator,terminal,console progress,console,bar,meter,rate
Platform: UNKNOWN
Classifier: Development Status :: 4 - Beta
Classifier: Environment :: Console
Classifier: Operating System :: OS Independent
Classifier: Programming Language :: Python :: 3.6
Classifier: Programming Language :: Python :: 3.7
Classifier: Intended Audience :: Developers
Classifier: Intended Audience :: System Administrators
Classifier: Topic :: Software Development :: Libraries
Classifier: Topic :: Utilities
Requires-Python: >=3.6
Requires-Dist: setuptools (==42.0.2)
